chatroutes_autobranch/__init__.py
chatroutes_autobranch/beam/__init__.py
chatroutes_autobranch/beam/selector.py
chatroutes_autobranch/budget/__init__.py
chatroutes_autobranch/budget/manager.py
chatroutes_autobranch/config/__init__.py
chatroutes_autobranch/config/loader.py
chatroutes_autobranch/core/__init__.py
chatroutes_autobranch/core/candidate.py
chatroutes_autobranch/core/embeddings.py
chatroutes_autobranch/core/protocols.py
chatroutes_autobranch/core/scorer.py
chatroutes_autobranch/core/selector.py
chatroutes_autobranch/entropy/__init__.py
chatroutes_autobranch/entropy/shannon.py
chatroutes_autobranch/novelty/__init__.py
chatroutes_autobranch/novelty/cosine.py
chatroutes_autobranch/novelty/mmr.py
chatroutes_autobranch-1.0.1.dist-info/licenses/LICENSE
chatroutes_autobranch-1.0.1.dist-info/METADATA
chatroutes_autobranch-1.0.1.dist-info/WHEEL
chatroutes_autobranch-1.0.1.dist-info/top_level.txt
chatroutes_autobranch-1.0.1.dist-info/RECORD
