Metadata-Version: 2.4
Name: chatroutes-autobranch
Version: 1.0.1
Summary: Intelligent branch exploration for LLM-powered applications
Author-email: ChatRoutes Team <hello@chatroutes.com>
License: MIT
Project-URL: Homepage, https://github.com/chatroutes/chatroutes-autobranch
Project-URL: Documentation, https://github.com/chatroutes/chatroutes-autobranch/blob/main/chatroutes_autobranch_v1.0.md
Project-URL: Repository, https://github.com/chatroutes/chatroutes-autobranch
Project-URL: Issues, https://github.com/chatroutes/chatroutes-autobranch/issues
Keywords: llm,beam-search,tree-of-thought,branching,ai,machine-learning
Classifier: Development Status :: 5 - Production/Stable
Classifier: Intended Audience :: Developers
Classifier: License :: OSI Approved :: MIT License
Classifier: Programming Language :: Python :: 3.9
Classifier: Programming Language :: Python :: 3.10
Classifier: Programming Language :: Python :: 3.11
Classifier: Programming Language :: Python :: 3.12
Classifier: Topic :: Scientific/Engineering :: Artificial Intelligence
Classifier: Topic :: Software Development :: Libraries :: Python Modules
Requires-Python: >=3.9
License-File: LICENSE
Requires-Dist: numpy>=1.24.0
Requires-Dist: scikit-learn>=1.3.0
Requires-Dist: pydantic>=2.0.0
Requires-Dist: pyyaml>=6.0
Provides-Extra: service
Requires-Dist: fastapi>=0.104.0; extra == "service"
Requires-Dist: uvicorn[standard]>=0.24.0; extra == "service"
Provides-Extra: hf
Requires-Dist: sentence-transformers>=2.2.0; extra == "hf"
Requires-Dist: torch>=2.0.0; extra == "hf"
Provides-Extra: faiss
Requires-Dist: faiss-cpu>=1.7.4; extra == "faiss"
Provides-Extra: dev
Requires-Dist: pytest>=7.4.0; extra == "dev"
Requires-Dist: pytest-cov>=4.1.0; extra == "dev"
Requires-Dist: pytest-benchmark>=4.0.0; extra == "dev"
Requires-Dist: mypy>=1.5.0; extra == "dev"
Requires-Dist: black>=23.9.0; extra == "dev"
Requires-Dist: ruff>=0.1.0; extra == "dev"
Requires-Dist: hypothesis>=6.88.0; extra == "dev"
Requires-Dist: pre-commit>=3.5.0; extra == "dev"
Provides-Extra: all
Requires-Dist: chatroutes-autobranch[dev,faiss,hf,service]; extra == "all"
Dynamic: license-file
